opennyai/__init__.py
opennyai/ner/InLegalNER/InLegalNER.py
opennyai/ner/InLegalNER/__init__.py
opennyai/ner/InLegalNER/entity_recognizer_utils.py
opennyai/ner/InLegalNER/postprocessing_utils.py
opennyai/ner/__init__.py
opennyai/ner/ner_utils.py
opennyai/pipeline.py
opennyai/rhetorical_roles/__init__.py
opennyai/rhetorical_roles/allennlp_helper/__init__.py
opennyai/rhetorical_roles/allennlp_helper/common/__init__.py
opennyai/rhetorical_roles/allennlp_helper/common/checks.py
opennyai/rhetorical_roles/allennlp_helper/common/from_params.py
opennyai/rhetorical_roles/allennlp_helper/common/lazy.py
opennyai/rhetorical_roles/allennlp_helper/common/params.py
opennyai/rhetorical_roles/allennlp_helper/common/registrable.py
opennyai/rhetorical_roles/allennlp_helper/common/util.py
opennyai/rhetorical_roles/allennlp_helper/modules/__init__.py
opennyai/rhetorical_roles/allennlp_helper/modules/conditional_random_field/__init__.py
opennyai/rhetorical_roles/allennlp_helper/modules/conditional_random_field/conditional_random_field.py
opennyai/rhetorical_roles/allennlp_helper/modules/conditional_random_field/conditional_random_field_wemission.py
opennyai/rhetorical_roles/allennlp_helper/modules/conditional_random_field/conditional_random_field_wlannoy.py
opennyai/rhetorical_roles/allennlp_helper/modules/conditional_random_field/conditional_random_field_wtrans.py
opennyai/rhetorical_roles/allennlp_helper/modules/encoder_base.py
opennyai/rhetorical_roles/allennlp_helper/modules/feedforward.py
opennyai/rhetorical_roles/allennlp_helper/modules/seq2seq_encoders/__init__.py
opennyai/rhetorical_roles/allennlp_helper/modules/seq2seq_encoders/compose_encoder.py
opennyai/rhetorical_roles/allennlp_helper/modules/seq2seq_encoders/feedforward_encoder.py
opennyai/rhetorical_roles/allennlp_helper/modules/seq2seq_encoders/gated_cnn_encoder.py
opennyai/rhetorical_roles/allennlp_helper/modules/seq2seq_encoders/pass_through_encoder.py
opennyai-0.0.13.dist-info/LICENSE
opennyai-0.0.13.dist-info/METADATA
opennyai-0.0.13.dist-info/WHEEL
opennyai-0.0.13.dist-info/RECORD
