Metadata-Version: 2.1
Name: opennyai
Version: 0.0.13
Summary: A SpaCy pipeline and models for NLP on indian legal text.
Author: Aman Tiwari
Author-email: work.amantiwari@gmail.com
Requires-Python: >=3.8,<4.0
Classifier: Programming Language :: Python :: 3
Classifier: Programming Language :: Python :: 3.8
Classifier: Programming Language :: Python :: 3.9
Classifier: Programming Language :: Python :: 3.10
Classifier: Programming Language :: Python :: 3.11
Requires-Dist: beautifulsoup4 (>=4.10.0)
Requires-Dist: levenshtein (>=0.23.0,<0.24.0)
Requires-Dist: multiprocess (>=0.70.15,<0.71.0)
Requires-Dist: nltk (>=3.6)
Requires-Dist: pandas (>1.2.4)
Requires-Dist: prettytable (>=3.1.1)
Requires-Dist: pytest (>=7.4.3,<8.0.0)
Requires-Dist: pytorch-transformers (>=1.2.0,<2.0.0)
Requires-Dist: scikit-learn (>=1.3.2,<2.0.0)
Requires-Dist: spacy (>=3.2.2,<3.3.0)
Requires-Dist: spacy-transformers (>=1.1.4)
Requires-Dist: torch (>=1.12.1)
